{
  "quizzes": [
    {
      "title": "General Knowledge",
      "description": "Test your general knowledge",
      "questions": [
        {
          "question": "What is the capital of France?",
          "imageUrl": "https://upload.wikimedia.org/wikipedia/commons/a/a8/Tour_Eiffel_Wikimedia_Commons.jpg",
          "options": ["Berlin", "Paris", "Madrid"],
          "correctIndex": 1
        },
        {
          "question": "Which planet is known as the Red Planet?",
          "imageUrl": null,
          "options": ["Earth", "Mars", "Jupiter"],
          "correctIndex": 1
        }
      ]
    },
    {
      "title": "Science",
      "description": "Basic science quiz",
      "questions": [
        {
          "question": "What is H2O?",
          "imageUrl": null,
          "options": ["Oxygen", "Water", "Hydrogen"],
          "correctIndex": 1
        }
      ]
    }
  ]
}
